<?xml version='1.0' encoding='utf-8'?>
<TextureAtlas imagePath="Matt.png">
<SubTexture name="MattHarpoonBit0000" x="1115" y="306" width="130" height="304" frameX="-42" frameY="0" frameWidth="211" frameHeight="317" />
<SubTexture name="MattHarpoonBit0001" x="1115" y="0" width="203" height="306" frameX="-4" frameY="-11" frameWidth="211" frameHeight="317" />
<SubTexture name="MattHarpoonIdle0000" x="1115" y="306" width="130" height="304" frameX="-42" frameY="0" frameWidth="211" frameHeight="317" />
<SubTexture name="MattPISSED0000" x="0" y="659" width="215" height="325" frameX="-10" frameY="-2" frameWidth="225" frameHeight="329" />
<SubTexture name="MattPISSED0001" x="0" y="659" width="215" height="325" frameX="-10" frameY="-2" frameWidth="225" frameHeight="329" />
<SubTexture name="MattPISSED0002" x="891" y="0" width="224" height="327" frameX="0" frameY="0" frameWidth="225" frameHeight="329" />
<SubTexture name="MattPISSED0003" x="891" y="0" width="224" height="327" frameX="0" frameY="0" frameWidth="225" frameHeight="329" />
<SubTexture name="MattPISSED0004" x="177" y="0" width="178" height="328" frameX="-45" frameY="0" frameWidth="225" frameHeight="329" />
<SubTexture name="MattPISSED0005" x="355" y="0" width="178" height="328" frameX="-45" frameY="0" frameWidth="225" frameHeight="329" />
<SubTexture name="MattPISSED0006" x="533" y="0" width="179" height="328" frameX="-45" frameY="0" frameWidth="225" frameHeight="329" />
<SubTexture name="MattPISSED0007" x="0" y="331" width="179" height="328" frameX="-45" frameY="0" frameWidth="225" frameHeight="329" />
<SubTexture name="MattReaction0000" x="0" y="0" width="177" height="331" frameX="-5" frameY="0" frameWidth="188" frameHeight="332" />
<SubTexture name="MattReactionTord0000" x="561" y="659" width="214" height="307" frameX="-2" frameY="-21" frameWidth="219" frameHeight="330" />
<SubTexture name="MattSnappingFinger0000" x="215" y="659" width="215" height="325" frameX="-10" frameY="-2" frameWidth="225" frameHeight="329" />
<SubTexture name="MattSnappingFinger0001" x="215" y="659" width="215" height="325" frameX="-10" frameY="-2" frameWidth="225" frameHeight="329" />
<SubTexture name="MattSnappingFinger0002" x="891" y="327" width="224" height="327" frameX="0" frameY="0" frameWidth="225" frameHeight="329" />
<SubTexture name="MattSnappingFinger0003" x="891" y="327" width="224" height="327" frameX="0" frameY="0" frameWidth="225" frameHeight="329" />
<SubTexture name="MattSnappingFinger0004" x="179" y="331" width="178" height="328" frameX="-45" frameY="0" frameWidth="225" frameHeight="329" />
<SubTexture name="MattSnappingFinger0005" x="357" y="331" width="178" height="328" frameX="-45" frameY="0" frameWidth="225" frameHeight="329" />
<SubTexture name="MattSnappingFinger0006" x="712" y="0" width="179" height="328" frameX="-45" frameY="0" frameWidth="225" frameHeight="329" />
<SubTexture name="MattSnappingFinger0007" x="712" y="328" width="179" height="328" frameX="-45" frameY="0" frameWidth="225" frameHeight="329" />
<SubTexture name="MattWalking0000" x="535" y="331" width="145" height="315" frameX="-19" frameY="0" frameWidth="164" frameHeight="321" />
<SubTexture name="MattWalking0001" x="430" y="659" width="131" height="309" frameX="-31" frameY="-9" frameWidth="164" frameHeight="321" />
<SubTexture name="MattWalking0002" x="1115" y="610" width="145" height="297" frameX="-14" frameY="-3" frameWidth="164" frameHeight="321" />
<SubTexture name="MattWalking0003" x="775" y="659" width="161" height="307" frameX="0" frameY="-1" frameWidth="164" frameHeight="321" />
</TextureAtlas>
